Metadata-Version: 2.1
Name: coinanalyse
Version: 1.0.5
Summary: Coin-help-package For Tr@ding bot.
Home-page: UNKNOWN
Author: Alice
License: Python Script
Platform: UNKNOWN
Provides-Extra: dev
License-File: LICENSE.txt
